zlibxjson/__init__.py
zlibxjson/main.py
zlibxjson-8.2.dist-info/METADATA
zlibxjson-8.2.dist-info/WHEEL
zlibxjson-8.2.dist-info/entry_points.txt
zlibxjson-8.2.dist-info/top_level.txt
zlibxjson-8.2.dist-info/RECORD
