Metadata-Version: 2.1
Name: zlibxjson
Version: 8.2
Summary: Package 
Home-page: https://github.com/votre_nom/votre_repository
Author: Votre Nom
Author-email: votre.email@example.com
Classifier: Programming Language :: Python :: 3
Classifier: License :: OSI Approved :: MIT License
Classifier: Operating System :: OS Independent
Requires-Python: >=3.6
Requires-Dist: requests
